profile_dists/__init__.py
profile_dists/constants.py
profile_dists/main.py
profile_dists/utils.py
profile_dists/version.py
profile_dists/test_data/__init__.py
profile_dists-1.0.10.dist-info/licenses/LICENSE
profile_dists-1.0.10.dist-info/METADATA
profile_dists-1.0.10.dist-info/WHEEL
profile_dists-1.0.10.dist-info/entry_points.txt
profile_dists-1.0.10.dist-info/top_level.txt
profile_dists-1.0.10.dist-info/RECORD
